Verilog_Scripts/BELIEF_PROPAGATION_LARGE_BLOCK_LENGTH_IMPLEMENTATION/minimum_second_minimum_calculator_control_path.v
//Control Path for Minimum and Second Minimum Calculator

`timescale 1ns/1ps

module minimum_second_minimum_calculator_control_path(clk, start_row_processing, done_row_processing, done_iterations, initialize_min, initialize_second_min, reset_count, calculating_second_min, load_first_min, load_second_min);
	input clk, start_row_processing, done_iterations;
	output reg done_row_processing, initialize_min, initialize_second_min, reset_count, calculating_second_min, load_first_min, load_second_min;

	parameter S0 = 0, S1 = 1, S2 = 2, S3 = 3, S4 = 4, S5 = 5;

	reg[2:0] present_state, next_state;

	always @(posedge clk) begin
		present_state <= next_state;
	end

	always @(*) begin
		case (present_state)
			S0: begin
				#2 if (start_row_processing) begin
					next_state = S1;
					load_first_min = 1; initialize_min = 1; calculating_second_min = 0; reset_count = 1;
				end
			end
			S1: begin
				#2 next_state = S2;
				initialize_min = 0; reset_count = 0;
			end
			S2: begin
				#2 if (done_iterations) begin
					next_state = S3;
					load_first_min = 0; load_second_min = 1; initialize_second_min = 1; calculating_second_min = 1; reset_count = 1;
				end
			end
			S3: begin
				#2 next_state = S4;
				initialize_second_min = 0; reset_count = 0;
			end
			S4: begin
				#2 if (done_iterations) begin
					next_state = S5;
					load_second_min = 0; done_row_processing = 1;
				end
			end
			S5: begin
				#2 next_state = S0;
				done_row_processing = 0; reset_count = 0; initialize_min = 0; initialize_second_min = 0; calculating_second_min = 0; load_first_min = 0; load_second_min = 0; 
			end
			default: begin
				#2 next_state = S0;
				done_row_processing = 0; reset_count = 0; initialize_min = 0; initialize_second_min = 0; calculating_second_min = 0; load_first_min = 0; load_second_min = 0;
			end
		endcase
	end
endmodule

Verilog_Scripts/Simple_LDPC_Belief_Propagation_Implementation/UP_COUNTER.v
//2 bit up counter with modification to skip the minimum position when
//calculating second minimum

`timescale 1ns/1ps

module UP_COUNTER(clk, reset, condition_check, min_index, count);
	input clk, reset, condition_check;
	input[1:0] min_index;
	output reg[1:0] count;
	
	reg[1:0] counter_input;
	wire reset_check;
	
	assign reset_check = (min_index == 2'b00) && condition_check;

	always @(*) begin
		counter_input = count + 1;
		if (counter_input == min_index && condition_check)
			counter_input = counter_input + 1;
	end

	always @(posedge clk or posedge reset) begin
		if (reset) begin
			if (reset_check)
				count <= 2'b01;
			else
				count <= 2'b00;
		end
		else begin
			count <= counter_input;
		end
	end
endmodule

Verilog_Scripts/Simple_LDPC_Belief_Propagation_Implementation/POS_PIPO_REGISTER.v
//2-bit parallel in parallel out register to store the minimum position

`timescale 1ns/1ps

module POS_PIPO_REGISTER(clk, load, out, in);
	input clk, load;
	input[1:0] in;
	output reg[1:0] out;

	always @(posedge clk) begin
		if (load)
			out <= in;
	end
endmodule

Verilog_Scripts/Simple_LDPC_Belief_Propagation_Implementation/BUS_MUX_21.v
//2 to 1 32-bit Bus Multiplexer

`timescale 1ns/1ps

module BUS_MUX_21(out, in1, in2, sel);
	input[31:0] in1, in2;
	output reg[31:0] out;
	input sel;

	always @(*) begin
		case (sel)
			1'b0: out = in1;
			1'b1: out = in2;
		endcase
	end
endmodule

Verilog_Scripts/Simple_LDPC_Belief_Propagation_Implementation/MIN_PIPO_REGISTER.v
//32 bit Parallel In Parallel Out Register to Store the Minimum and Second
//Minimum

`timescale 1ns/1ps

module MIN_PIPO_REGISTER(clk, load, initialize, out, in);
	input clk, load, initialize;
	input[31:0] in;
	output reg[31:0] out;

	always @(posedge clk or posedge initialize) begin
		if (initialize)
			out <= 32'hFFFFFFFF;
		else if (load)
			out <= in;
	end
endmodule

Verilog_Scripts/Simple_LDPC_Belief_Propagation_Implementation/comparator_exponent.v
`timescale 1ns/1ps

module comparator_exponent(l, g, in1, in2);
	input[7:0] in1;
	input[7:0] in2;
	output l, g;

	assign l = in1 < in2;
	assign g = in1 > in2;
endmodule

Verilog_Scripts/BELIEF_PROPAGATION_LARGE_BLOCK_LENGTH_IMPLEMENTATION/comparator_mantissa.v
`timescale 1ns/1ps

module comparator_mantissa(l, in1, in2);
	input[22:0] in1, in2;
	output l;

	assign l = (in1 < in2);
endmodule

Verilog_Scripts/Simple_LDPC_Belief_Propagation_Implementation/comparator_floating_point.v
`timescale 1ns/1ps

module comparator_floating_point(l, in1, in2);
	input[31:0] in1, in2;
	output l;

	wire mantissa_l;
	wire exponent_l, exponent_g;
	wire t0, t1;

	comparator_mantissa COMPARE_MANTISSAS(mantissa_l, in1[22:0], in2[22:0]);
	comparator_exponent COMPARE_EXPONENTS(exponent_l, exponent_g, in1[30:23], in2[30:23]);
	not G1(t0, exponent_g);
	and G2(t1, mantissa_l, t0);
	or G3(l, exponent_l, t1);
endmodule

Verilog_Scripts/Simple_LDPC_Belief_Propagation_Implementation/BUS_MUX_31.v
//3 - to - 1 32 bit Bus Multiplexer

`timescale 1ns/1ps

module BUS_MUX_31(out, in1, in2, in3, sel);
	input[31:0] in1, in2, in3;
	output reg[31:0] out;
	input[1:0] sel;

	always @(*) begin
		case (sel)
			2'b00: out = in1;
			2'b01: out = in2;
			2'b10: out = in3;
			default: out = 32'b0;
		endcase
	end
endmodule

Verilog_Scripts/Simple_LDPC_Belief_Propagation_Implementation/minimum_second_minimum_calculator_data_path.v
//Datapath of Check Node Processor that Calculates Absolute Minimum and Absolute Second Minimum

`timescale 1ns/1ps

module minimum_second_minimum_calculator_data_path(clk, done_iterations, initialize_min, initialize_second_min, reset_count, calculating_second_min, r1, r2, r3, min, second_min, pos, load_first_min, load_second_min);
	input[31:0] r1, r2, r3;
	output[31:0] min, second_min;
	output[1:0] pos;
	input clk, initialize_min, initialize_second_min, reset_count, calculating_second_min, load_first_min, load_second_min;
	output done_iterations;

	wire[31:0] r1_out, r2_out, r3_out;
	wire[31:0] comparator_input_1, comparator_input_2, comparator_out;
	wire[31:0] minimum_out, second_minimum_out;
	wire[1:0] count;
	wire calculating_first_minimum;
	wire load_pos;
	wire l;

	assign r1_out = r1;
	assign r2_out = r2;
	assign r3_out = r3;
	assign done_iterations = (count >= 2'b11);
	assign min = minimum_out;
	assign second_min = second_minimum_out;

	BUS_MUX_31 generate_first_comparator_input(comparator_input_1, r1_out, r2_out, r3_out, count);
	comparator_floating_point generate_comparator_less_than_output(l, comparator_input_1, comparator_input_2);
	BUS_MUX_21 generate_comparator_output(comparator_out, comparator_input_2, comparator_input_1, l);
	MIN_PIPO_REGISTER minimum_register(clk, load_first_min, initialize_min, minimum_out, comparator_out);
	MIN_PIPO_REGISTER second_minimum_register(clk, load_second_min, initialize_second_min, second_minimum_out, comparator_out);
	BUS_MUX_21 generate_second_comparator_input(comparator_input_2, minimum_out, second_minimum_out, calculating_second_min);
	and G2(load_pos, load_first_min, l);
	POS_PIPO_REGISTER pos_register(clk, load_pos, pos, count);
	UP_COUNTER calculate_count(clk, reset_count, calculating_second_min, pos, count);
endmodule

Verilog_Scripts/Simple_LDPC_Belief_Propagation_Implementation/minimum_second_minimum_calculator_test_bench.v
//Test Bench for Row Processing Operation

`timescale 1ns/1ps

module minimum_second_minimum_calculator_test_bench;
	reg clk, start_row_processing;
	reg[31:0] r1, r2, r3;
	wire[31:0] min, second_min;
	wire[1:0] pos;

	minimum_second_minimum_calculator_data_path DATA_PATH_DUT(clk, done_iterations, initialize_min, initialize_second_min, reset_count, calculating_second_min, r1, r2, r3, min, second_min, pos, load_first_min, load_second_min);
	minimum_second_minimum_calculator_control_path CONTROL_PATH_DUT(clk, start_row_processing, done_row_processing, done_iterations, initialize_min, initialize_second_min, reset_count, calculating_second_min, load_first_min, load_second_min);

	initial clk = 1'b0;

	always #5 clk = ~clk;

	initial begin
		$dumpfile("minimum_second_minimum_calculator.vcd");
		$dumpvars(0, minimum_second_minimum_calculator_test_bench);
		$monitor($time, ": Minimum = %32b, Position of Minimum = %2b, Second Minimum = %32b", min, pos, second_min);
		r3 = 32'b00111111100110011001100110011010; r1 = 32'b01000010110010000000000000000000; r2 = 32'b00111110100110011001100110011001;
		//r3 = 1.2 r1 = 100 r2 = 0.3
		#2 start_row_processing = 1'b1;
		#10 start_row_processing = 1'b0;
		#100 $finish;
	end
endmodule

Verilog_Scripts/Simple_LDPC_Belief_Propagation_Implementation/minimum_second_minimum_calculator.vcd
$date
	Fri Feb 10 20:03:17 2023
$end
$version
	Icarus Verilog
$end
$timescale
	1ps
$end
$scope module minimum_second_minimum_calculator_test_bench $end
$var wire 32 ! second_min [31:0] $end
$var wire 1 " reset_count $end
$var wire 2 # pos [1:0] $end
$var wire 32 $ min [31:0] $end
$var wire 1 % load_second_min $end
$var wire 1 & load_first_min $end
$var wire 1 ' initialize_second_min $end
$var wire 1 ( initialize_min $end
$var wire 1 ) done_row_processing $end
$var wire 1 * done_iterations $end
$var wire 1 + calculating_second_min $end
$var reg 1 , clk $end
$var reg 32 - r1 [31:0] $end
$var reg 32 . r2 [31:0] $end
$var reg 32 / r3 [31:0] $end
$var reg 1 0 start_row_processing $end
$scope module CONTROL_PATH_DUT $end
$var wire 1 , clk $end
$var wire 1 0 start_row_processing $end
$var wire 1 * done_iterations $end
$var reg 1 + calculating_second_min $end
$var reg 1 ) done_row_processing $end
$var reg 1 ( initialize_min $end
$var reg 1 ' initialize_second_min $end
$var reg 1 & load_first_min $end
$var reg 1 % load_second_min $end
$var reg 3 1 next_state [2:0] $end
$var reg 3 2 present_state [2:0] $end
$var reg 1 " reset_count $end
$upscope $end
$scope module DATA_PATH_DUT $end
$var wire 1 + calculating_second_min $end
$var wire 1 , clk $end
$var wire 1 ( initialize_min $end
$var wire 1 ' initialize_second_min $end
$var wire 1 & load_first_min $end
$var wire 1 3 load_pos $end
$var wire 1 % load_second_min $end
$var wire 32 4 min [31:0] $end
$var wire 32 5 r1 [31:0] $end
$var wire 32 6 r1_out [31:0] $end
$var wire 32 7 r2 [31:0] $end
$var wire 32 8 r2_out [31:0] $end
$var wire 32 9 r3 [31:0] $end
$var wire 32 : r3_out [31:0] $end
$var wire 1 " reset_count $end
$var wire 32 ; second_min [31:0] $end
$var wire 32 < second_minimum_out [31:0] $end
$var wire 2 = pos [1:0] $end
$var wire 32 > minimum_out [31:0] $end
$var wire 1 ? l $end
$var wire 1 * done_iterations $end
$var wire 2 @ count [1:0] $end
$var wire 32 A comparator_out [31:0] $end
$var wire 32 B comparator_input_2 [31:0] $end
$var wire 32 C comparator_input_1 [31:0] $end
$scope module calculate_count $end
$var wire 1 , clk $end
$var wire 1 + condition_check $end
$var wire 1 " reset $end
$var wire 1 D reset_check $end
$var wire 2 E min_index [1:0] $end
$var reg 2 F count [1:0] $end
$var reg 2 G counter_input [1:0] $end
$upscope $end
$scope module generate_comparator_less_than_output $end
$var wire 1 ? l $end
$var wire 1 H t0 $end
$var wire 1 I t1 $end
$var wire 1 J mantissa_l $end
$var wire 32 K in2 [31:0] $end
$var wire 32 L in1 [31:0] $end
$var wire 1 M exponent_l $end
$var wire 1 N exponent_g $end
$scope module COMPARE_EXPONENTS $end
$var wire 8 O in1 [7:0] $end
$var wire 8 P in2 [7:0] $end
$var wire 1 M l $end
$var wire 1 N g $end
$upscope $end
$scope module COMPARE_MANTISSAS $end
$var wire 23 Q in1 [22:0] $end
$var wire 23 R in2 [22:0] $end
$var wire 1 J l $end
$upscope $end
$upscope $end
$scope module generate_comparator_output $end
$var wire 1 ? sel $end
$var wire 32 S in2 [31:0] $end
$var wire 32 T in1 [31:0] $end
$var reg 32 U out [31:0] $end
$upscope $end
$scope module generate_first_comparator_input $end
$var wire 32 V in1 [31:0] $end
$var wire 32 W in2 [31:0] $end
$var wire 32 X in3 [31:0] $end
$var wire 2 Y sel [1:0] $end
$var reg 32 Z out [31:0] $end
$upscope $end
$scope module generate_second_comparator_input $end
$var wire 1 + sel $end
$var wire 32 [ in2 [31:0] $end
$var wire 32 \ in1 [31:0] $end
$var reg 32 ] out [31:0] $end
$upscope $end
$scope module minimum_register $end
$var wire 1 , clk $end
$var wire 32 ^ in [31:0] $end
$var wire 1 ( initialize $end
$var wire 1 & load $end
$var reg 32 _ out [31:0] $end
$upscope $end
$scope module pos_register $end
$var wire 1 , clk $end
$var wire 2 ` in [1:0] $end
$var wire 1 3 load $end
$var reg 2 a out [1:0] $end
$upscope $end
$scope module second_minimum_register $end
$var wire 1 , clk $end
$var wire 32 b in [31:0] $end
$var wire 1 ' initialize $end
$var wire 1 % load $end
$var reg 32 c out [31:0] $end
$upscope $end
$upscope $end
$upscope $end
$enddefinitions $end
#0
$dumpvars
bx c
bx b
bx a
bx `
bx _
bx ^
bx ]
bx \
bx [
b0 Z
bx Y
b111111100110011001100110011010 X
b111110100110011001100110011001 W
b1000010110010000000000000000000 V
bx U
bx T
b0 S
bx R
b0 Q
bx P
b0 O
xN
xM
b0 L
bx K
xJ
xI
xH
bx G
bx F
bx E
xD
b0 C
bx B
bx A
bx @
x?
bx >
bx =
bx <
bx ;
b111111100110011001100110011010 :
b111111100110011001100110011010 9
b111110100110011001100110011001 8
b111110100110011001100110011001 7
b1000010110010000000000000000000 6
b1000010110010000000000000000000 5
bx 4
x3
bx 2
bx 1
x0
b111111100110011001100110011010 /
b111110100110011001100110011001 .
b1000010110010000000000000000000 -
0,
x+
x*
x)
x(
x'
x&
x%
bx $
bx #
x"
bx !
$end
#2000
10
#4000
03
0D
0%
0&
0+
0'
0(
0"
0)
b0 1
#5000
b0 2
1,
#7000
b1000010110010000000000000000000 A
b1000010110010000000000000000000 U
b1000010110010000000000000000000 ^
b1000010110010000000000000000000 b
1I
1?
1H
b10000101 O
b10010000000000000000000 Q
1M
0N
b11111111 P
1J
b11111111111111111111111 R
b1 G
b1000010110010000000000000000000 C
b1000010110010000000000000000000 L
b1000010110010000000000000000000 S
b1000010110010000000000000000000 Z
b11111111111111111111111111111111 B
b11111111111111111111111111111111 K
b11111111111111111111111111111111 T
b11111111111111111111111111111111 ]
0*
b0 @
b0 F
b0 Y
b0 `
b11111111111111111111111111111111 $
b11111111111111111111111111111111 4
b11111111111111111111111111111111 >
b11111111111111111111111111111111 \
b11111111111111111111111111111111 _
13
1"
1(
1&
b1 1
#10000
0,
#12000
00
#15000
b1 2
b0 #
b0 =
b0 E
b0 a
1,
#17000
0"
0(
b10 1
#20000
0,
#25000
b1111101 O
b110011001100110011001 Q
1M
b10000101 P
1J
b10010000000000000000000 R
b111110100110011001100110011001 A
b111110100110011001100110011001 U
b111110100110011001100110011001 ^
b111110100110011001100110011001 b
b10 G
b111110100110011001100110011001 C
b111110100110011001100110011001 L
b111110100110011001100110011001 S
b111110100110011001100110011001 Z
b1000010110010000000000000000000 B
b1000010110010000000000000000000 K
b1000010110010000000000000000000 T
b1000010110010000000000000000000 ]
b10 2
b1 @
b1 F
b1 Y
b1 `
b1000010110010000000000000000000 $
b1000010110010000000000000000000 4
b1000010110010000000000000000000 >
b1000010110010000000000000000000 \
b1000010110010000000000000000000 _
1,
#30000
0,
#35000
03
0H
0?
0I
1N
b1111111 O
b110011001100110011010 Q
0M
b1111101 P
0J
b110011001100110011001 R
b111110100110011001100110011001 A
b111110100110011001100110011001 U
b111110100110011001100110011001 ^
b111110100110011001100110011001 b
b11 G
b111111100110011001100110011010 C
b111111100110011001100110011010 L
b111111100110011001100110011010 S
b111111100110011001100110011010 Z
b111110100110011001100110011001 B
b111110100110011001100110011001 K
b111110100110011001100110011001 T
b111110100110011001100110011001 ]
b1 #
b1 =
b1 E
b1 a
b10 @
b10 F
b10 Y
b10 `
b111110100110011001100110011001 $
b111110100110011001100110011001 4
b111110100110011001100110011001 >
b111110100110011001100110011001 \
b111110100110011001100110011001 _
1,
#40000
0,
#45000
b0 A
b0 U
b0 ^
b0 b
13
1I
1?
1H
1M
0N
b0 O
1J
b0 Q
b0 G
b0 C
b0 L
b0 S
b0 Z
1*
b11 @
b11 F
b11 Y
b11 `
1,
#47000
b1000010110010000000000000000000 A
b1000010110010000000000000000000 U
b1000010110010000000000000000000 ^
b1000010110010000000000000000000 b
b10000101 O
b10010000000000000000000 Q
b10 G
b1000010110010000000000000000000 C
b1000010110010000000000000000000 L
b1000010110010000000000000000000 S
b1000010110010000000000000000000 Z
0*
b0 @
b0 F
b0 Y
b0 `
b11111111111111111111111111111111 !
b11111111111111111111111111111111 ;
b11111111111111111111111111111111 <
b11111111111111111111111111111111 [
b11111111111111111111111111111111 c
1?
1H
1I
1M
0N
b11111111 P
1J
b11111111111111111111111 R
b11111111111111111111111111111111 B
b11111111111111111111111111111111 K
b11111111111111111111111111111111 T
b11111111111111111111111111111111 ]
03
1"
1+
1'
1%
0&
b11 1
#50000
0,
#55000
b11 2
1,
#57000
0"
0'
b100 1
#60000
0,
#65000
b1111111 O
b110011001100110011010 Q
1M
b10000101 P
1J
b10010000000000000000000 R
b111111100110011001100110011010 A
b111111100110011001100110011010 U
b111111100110011001100110011010 ^
b111111100110011001100110011010 b
b11 G
b111111100110011001100110011010 C
b111111100110011001100110011010 L
b111111100110011001100110011010 S
b111111100110011001100110011010 Z
b1000010110010000000000000000000 B
b1000010110010000000000000000000 K
b1000010110010000000000000000000 T
b1000010110010000000000000000000 ]
b100 2
b10 @
b10 F
b10 Y
b10 `
b1000010110010000000000000000000 !
b1000010110010000000000000000000 ;
b1000010110010000000000000000000 <
b1000010110010000000000000000000 [
b1000010110010000000000000000000 c
1,
#70000
0,
#75000
b0 O
b0 Q
1M
b1111111 P
1J
b110011001100110011010 R
b0 A
b0 U
b0 ^
b0 b
b0 G
b0 C
b0 L
b0 S
b0 Z
b111111100110011001100110011010 B
b111111100110011001100110011010 K
b111111100110011001100110011010 T
b111111100110011001100110011010 ]
1*
b11 @
b11 F
b11 Y
b11 `
b111111100110011001100110011010 !
b111111100110011001100110011010 ;
b111111100110011001100110011010 <
b111111100110011001100110011010 [
b111111100110011001100110011010 c
1,
#77000
1)
0%
b101 1
#80000
0,
#85000
0?
0H
0I
0M
1N
b10000101 O
0J
b10010000000000000000000 Q
b111111100110011001100110011010 A
b111111100110011001100110011010 U
b111111100110011001100110011010 ^
b111111100110011001100110011010 b
b10 G
b1000010110010000000000000000000 C
b1000010110010000000000000000000 L
b1000010110010000000000000000000 S
b1000010110010000000000000000000 Z
b101 2
0*
b0 @
b0 F
b0 Y
b0 `
1,
#87000
b1111101 P
b110011001100110011001 R
b111110100110011001100110011001 A
b111110100110011001100110011001 U
b111110100110011001100110011001 ^
b111110100110011001100110011001 b
b1 G
b111110100110011001100110011001 B
b111110100110011001100110011001 K
b111110100110011001100110011001 T
b111110100110011001100110011001 ]
0+
0)
b0 1
#90000
0,
#95000
1H
0N
b1111101 O
b110011001100110011001 Q
b10 G
b111110100110011001100110011001 C
b111110100110011001100110011001 L
b111110100110011001100110011001 S
b111110100110011001100110011001 Z
b0 2
b1 @
b1 F
b1 Y
b1 `
1,
#100000
0,
#105000
0H
1N
b1111111 O
b110011001100110011010 Q
b11 G
b111111100110011001100110011010 C
b111111100110011001100110011010 L
b111111100110011001100110011010 S
b111111100110011001100110011010 Z
b10 @
b10 F
b10 Y
b10 `
1,
