Verilog_Scripts/Simple_LDPC_Belief_Propagation_Implementation/UP_COUNTER.v
//2 bit up counter with modification to skip the minimum position when
//calculating second minimum

`timescale 1ns/1ps

module UP_COUNTER(clk, reset, condition_check, min_index, count);
	input clk, reset, condition_check;
	input[1:0] min_index;
	output reg[1:0] count;
	
	reg[1:0] counter_input;
	wire reset_check;
	
	assign reset_check = (min_index == 2'b00) && condition_check;

	always @(*) begin
		counter_input = count + 1;
		if (counter_input == min_index && condition_check)
			counter_input = counter_input + 1;
	end

	always @(posedge clk or posedge reset) begin
		if (reset) begin
			if (reset_check)
				count <= 2'b01;
			else
				count <= 2'b00;
		end
		else begin
			count <= counter_input;
		end
	end
endmodule

Verilog_Scripts/Simple_LDPC_Belief_Propagation_Implementation/UP_COUNTER_TEST_BENCH.v
//Test Bench for Up Counter

module UP_COUNTER_TEST_BENCH;
	reg clk, reset, condition_check;
	reg[1:0] min_index;
	wire[1:0] count;

	UP_COUNTER DUT(clk, reset, condition_check, min_index, count);

	initial clk = 1'b0;

	always #5 clk = ~clk;

	initial begin
		$dumpfile("UP_COUNTER.vcd");
		$dumpvars(0, UP_COUNTER_TEST_BENCH);
		$monitor($time, ": count = %2b", count);
		#2 reset = 1'b1; condition_check = 1'b1; min_index = 2'b11;
		#5 reset = 1'b0;
		#100 $finish;
	end
endmodule

Verilog_Scripts/Simple_LDPC_Belief_Propagation_Implementation/UP_COUNTER.vcd
$date
	Fri Feb 10 12:19:51 2023
$end
$version
	Icarus Verilog
$end
$timescale
	1ps
$end
$scope module UP_COUNTER_TEST_BENCH $end
$var wire 2 ! count [1:0] $end
$var reg 1 " clk $end
$var reg 1 # condition_check $end
$var reg 2 $ min_index [1:0] $end
$var reg 1 % reset $end
$scope module DUT $end
$var wire 1 " clk $end
$var wire 1 # condition_check $end
$var wire 2 & min_index [1:0] $end
$var wire 1 % reset $end
$var wire 1 ' reset_check $end
$var reg 2 ( count [1:0] $end
$var reg 2 ) counter_input [1:0] $end
$upscope $end
$upscope $end
$enddefinitions $end
#0
$dumpvars
bx )
bx (
x'
bx &
x%
bx $
x#
0"
bx !
$end
#2000
b1 )
b0 !
b0 (
0'
b11 $
b11 &
1#
1%
#5000
1"
#7000
0%
#10000
0"
#15000
b10 )
b1 !
b1 (
1"
#20000
0"
#25000
b0 )
b10 !
b10 (
1"
#30000
0"
#35000
b1 )
b0 !
b0 (
1"
#40000
0"
#45000
b10 )
b1 !
b1 (
1"
#50000
0"
#55000
b0 )
b10 !
b10 (
1"
#60000
0"
#65000
b1 )
b0 !
b0 (
1"
#70000
0"
#75000
b10 )
b1 !
b1 (
1"
#80000
0"
#85000
b0 )
b10 !
b10 (
1"
#90000
0"
#95000
b1 )
b0 !
b0 (
1"
#100000
0"
#105000
b10 )
b1 !
b1 (
1"
