Verilog_Scripts/QC_LDPC_Encoder/QC_LDPC_CONTROL_PATH.v
//Modelling the Control Path of QCLDPC Encoder

`timescale 1ns/1ps

module QC_LDPC_ENCODER_CONTROL_PATH(clk, clear_5bit_counter, clear_2bit_counter, increment_2bit_counter, load_SRAA_shift_reg, load_SRAA_reg, clear_SRAA, counter_5bit_out, counter_2bit_out, start, done);
	input clk, start;
	input[1:0] counter_2bit_out;
	input[4:0] counter_5bit_out;
	output reg clear_2bit_counter, clear_5bit_counter, load_SRAA_shift_reg, load_SRAA_reg;
	output reg clear_SRAA, increment_2bit_counter, done;

	reg[2:0] PS, NS;

	parameter S0 = 0, S1 = 1, S2 = 2, S3 = 3, S4 = 4, S5 = 5;

	always @(posedge clk) begin
		PS <= NS;
	end

	always @(*) begin
		case (PS)
			S0: begin
				#2 if (start) begin
					NS = S1;
					clear_2bit_counter = 1; clear_5bit_counter = 1; clear_SRAA = 1; load_SRAA_shift_reg = 1;
				end
			end
			S1: begin
				#2 NS = S2;
				clear_2bit_counter = 0; clear_5bit_counter = 0; clear_SRAA = 0; load_SRAA_shift_reg = 0; load_SRAA_reg = 1;
			end
			S2: begin
				#2 if (counter_2bit_out == 2'b10) begin
					if (counter_5bit_out == 1) begin
						NS = S5;
						done = 1;
						clear_2bit_counter = 0; clear_5bit_counter = 0; load_SRAA_shift_reg = 0; load_SRAA_reg = 0;
						clear_SRAA = 0; increment_2bit_counter = 0;
					end
				end
				else begin
					if (counter_5bit_out == 14) begin
						NS = S3;
						increment_2bit_counter = 1;
					end
				end
			end
			S3: begin
				#2 NS = S4;
				increment_2bit_counter = 0; clear_5bit_counter = 1; load_SRAA_shift_reg = 1;
			end
			S4: begin
				#2 NS = S2;
				load_SRAA_shift_reg = 0; clear_5bit_counter = 0;
			end
			S5: begin
				#2 NS = S5;
				done = 1;
				clear_2bit_counter = 0; clear_5bit_counter = 0; load_SRAA_shift_reg = 0; load_SRAA_reg = 0;
				clear_SRAA = 0; increment_2bit_counter = 0;
			end
			default: begin
				#2 NS = S0;
				clear_2bit_counter = 0; clear_5bit_counter = 0; load_SRAA_shift_reg = 0; load_SRAA_reg = 0;
				clear_SRAA = 0; increment_2bit_counter = 0; done = 0;
			end
		endcase
	end
endmodule

Verilog_Scripts/QC_LDPC_Encoder/COUNTER_5BIT.v
//Modelling a 5-bit Counter

`timescale 1ns/1ps

module COUNTER_5BIT(clk, clear, count);
	input clear, clk;
	output reg[4:0] count;

	always @(posedge clk or posedge clear) begin
		if (clear)
			count <= 5'b0;
		else
			count <= count + 1;
	end
endmodule

Verilog_Scripts/QC_LDPC_Encoder/COUNTER_2BIT.v
//Modelling a 2 bit counter

`timescale 1ns/1ps

module COUNTER_2BIT(clk, clear, increment, count);
	input clear, clk, increment;
	output reg[1:0] count;

	always @(posedge clk or posedge clear) begin
		if (clear)
			count <= 2'b00;
		else if (increment)
			count <= count + 1;
	end
endmodule

Verilog_Scripts/QC_LDPC_Encoder_Small_Block_Lengths/MUX_31.v
//Modelling a 16 bit 3 to one multiplexer

`timescale 1ns/1ps

module MUX31_16bit(out, in1, in2, in3, sel);
	input[31:0] in1, in2, in3;
	input[1:0] sel;
	output reg[31:0] out;

	always @(*) begin
		if (sel == 2'b00)
			out = in1;
		else if (sel == 2'b01)
			out = in2;
		else if (sel == 2'b10)
			out = in3;
		else
			out = 16'b0;
	end
endmodule

Verilog_Scripts/QC_LDPC_Encoder/SHIFT_REGISTER_16BIT.v
//Modelling a 16 bit shift register

`timescale 1ns/1ps

module SHIFT_REGISTER_16_BIT(clk, clear, load, in, out);
	input clk, clear, load;
	input[15:0] in;
	output reg[15:0] out;

	always @(posedge clk or posedge clear) begin
		if (clear)
			out <= 16'b0;
		else if (load) 
			out <= in;
	end
endmodule

Verilog_Scripts/QC_LDPC_Encoder/CYCLIC_SHIFT_REGISTER_16BIT.v
//Module to implement a 16 bit cyclic shift register

`timescale 1ns/1ps

module CYCLIC_SHIFT_REGISTER_16BIT(clk, load, in, out);
	input clk, load;
	input[15:0] in;
	output reg[15:0] out;

	always @(posedge clk) begin
		if (load)
			out <= in;
		else
			out <= {out[0], out[15:1]};
	end
endmodule

Verilog_Scripts/QC_LDPC_Encoder/SRAA_16BIT.v
//Modelling a 16 bit Shift Register Add Accumulate Circuit

`timescale 1ns/1ps

module SRAA_16BIT(clk, load_shift_reg, load_reg, clear, in, out, info_bit);
	input clk, load, clear;
	input info_bit;
	input[15:0] in;
	output[15:0] out;
	input load_shift_reg, load_reg;

	wire[15:0] current_gi;
	reg[15:0] temp;
	reg[15:0] reg_in;
	integer iterator;

	CYCLIC_SHIFT_REGISTER_16BIT current_gi_calculator(clk, load_shift_reg, in, current_gi);
	SHIFT_REGISTER_16_BIT generate_final_output(clk, clear, load_reg, reg_in, out);

	always @(*) begin
		for (iterator = 0; iterator <= 15; iterator = iterator + 1) begin
			temp[iterator] = current_gi[iterator] & info_bit;
			reg_in[iterator] = out[iterator] ^ temp[iterator];
		end
	end
endmodule

Verilog_Scripts/QC_LDPC_Encoder_Small_Block_Lengths/QC_LDPC_DATA_PATH.v
//Modelling the Data Path of the Encoder

`timescale 1ns/1ps

module QC_LDPC_ENCODER_DATA_PATH(clk, clear_5bit_counter, clear_2bit_counter, increment_2bit_counter, load_SRAA_shift_reg, load_SRAA_reg, clear_SRAA, G_row_1, G_row_2, Q_row, counter_5bit_out, counter_2bit_out, info_bit, generated_vector);
	input clk, clear_5bit_counter, clear_2bit_counter, increment_2bit_counter, load_SRAA_shift_reg, load_SRAA_reg, clear_SRAA;
	input[31:0] G_row_1, G_row_2, Q_row;
	input info_bit;
	output[31:0] generated_vector;
	output[4:0] counter_5bit_out;
	output[1:0] counter_2bit_out;

	wire[31:0] SRAA_in;

	SRAA_16BIT sraa_1(clk, load_SRAA_shift_reg, load_SRAA_reg, clear_SRAA, SRAA_in[31:16], generated_vector[31:16], info_bit);
	SRAA_16BIT sraa_2(clk, load_SRAA_shift_reg, load_SRAA_reg, clear_SRAA, SRAA_in[15:0], generated_vector[15:0], info_bit);
	MUX31_16bit select_sraa_input(SRAA_in, G_row_1, G_row_2, Q_row, counter_2bit_out);
	COUNTER_2BIT row_block_indicator(clk, clear_2bit_counter, increment_2bit_counter, counter_2bit_out);
	COUNTER_5BIT row_indicator(clk, clear_5bit_counter, counter_5bit_out);
endmodule

Verilog_Scripts/QC_LDPC_Encoder_Small_Block_Lengths/QC_LDPC_ENCODER_TEST_BENCH.v
//Test Bench for the Encoder

`timescale 1ns/1ps

module QC_LDPC_ENCODER_TEST_BENCH;
	reg start;
	reg info_bit;
	reg clk;
	reg[32:0] info_vector;
	reg[31:0] G_row_1, G_row_2, Q_row;
	wire done;
	wire[31:0] generated_vector;
	wire[4:0] counter_5bit_out;
	wire[1:0] counter_2bit_out;
	integer iterator;

	QC_LDPC_ENCODER_DATA_PATH DUT_DATA_PATH(clk, clear_5bit_counter, clear_2bit_counter, increment_2bit_counter, load_SRAA_shift_reg, load_SRAA_reg, clear_SRAA, G_row_1, G_row_2, Q_row, counter_5bit_out, counter_2bit_out, info_bit, generated_vector);
	QC_LDPC_ENCODER_CONTROL_PATH DUT_CONTROL_PATH(clk, clear_5bit_counter, clear_2bit_counter, increment_2bit_counter, load_SRAA_shift_reg, load_SRAA_reg, clear_SRAA, counter_5bit_out, counter_2bit_out, start, done);

	initial info_vector = 33'b110000111111000101001101110110111;

	initial begin
		G_row_1 = 32'b11111110000000110000111111110000;
		G_row_2 = 32'b11110000001111111111111110000000;
	       	Q_row = 32'b11111111111111111111111111111111;
	end

	initial clk = 1'b0;
	always #5 clk = ~clk;

	initial begin
		$dumpfile("QC_LDPC_ENCODER.vcd");
		$dumpvars(0, QC_LDPC_ENCODER_TEST_BENCH);
		$monitor($time, ": Last 32 Bits of Code Word = %32b", generated_vector);
		#2 start = 1'b1;
		#10 start = 1'b0;
		for (iterator = 32; iterator >= 0; iterator = iterator - 1) begin
			#10 info_bit = info_vector[iterator];
		end
		#100 $finish;
	end
endmodule

Verilog_Scripts/QC_LDPC_Encoder/QC_LDPC_ENCODER.vcd
$date
	Tue Mar  7 12:50:19 2023
$end
$version
	Icarus Verilog
$end
$timescale
	1ps
$end
$scope module QC_LDPC_ENCODER_TEST_BENCH $end
$var wire 1 ! load_SRAA_shift_reg $end
$var wire 1 " load_SRAA_reg $end
$var wire 1 # increment_2bit_counter $end
$var wire 32 $ generated_vector [31:0] $end
$var wire 1 % done $end
$var wire 5 & counter_5bit_out [4:0] $end
$var wire 2 ' counter_2bit_out [1:0] $end
$var wire 1 ( clear_SRAA $end
$var wire 1 ) clear_5bit_counter $end
$var wire 1 * clear_2bit_counter $end
$var reg 32 + G_row_1 [31:0] $end
$var reg 32 , G_row_2 [31:0] $end
$var reg 32 - Q_row [31:0] $end
$var reg 1 . clk $end
$var reg 1 / info_bit $end
$var reg 33 0 info_vector [32:0] $end
$var reg 1 1 start $end
$var integer 32 2 iterator [31:0] $end
$scope module DUT_CONTROL_PATH $end
$var wire 1 . clk $end
$var wire 1 1 start $end
$var wire 5 3 counter_5bit_out [4:0] $end
$var wire 2 4 counter_2bit_out [1:0] $end
$var reg 3 5 NS [2:0] $end
$var reg 3 6 PS [2:0] $end
$var reg 1 * clear_2bit_counter $end
$var reg 1 ) clear_5bit_counter $end
$var reg 1 ( clear_SRAA $end
$var reg 1 % done $end
$var reg 1 # increment_2bit_counter $end
$var reg 1 " load_SRAA_reg $end
$var reg 1 ! load_SRAA_shift_reg $end
$upscope $end
$scope module DUT_DATA_PATH $end
$var wire 32 7 G_row_1 [31:0] $end
$var wire 32 8 G_row_2 [31:0] $end
$var wire 32 9 Q_row [31:0] $end
$var wire 1 * clear_2bit_counter $end
$var wire 1 ) clear_5bit_counter $end
$var wire 1 ( clear_SRAA $end
$var wire 1 . clk $end
$var wire 1 # increment_2bit_counter $end
$var wire 1 / info_bit $end
$var wire 1 " load_SRAA_reg $end
$var wire 1 ! load_SRAA_shift_reg $end
$var wire 32 : generated_vector [31:0] $end
$var wire 5 ; counter_5bit_out [4:0] $end
$var wire 2 < counter_2bit_out [1:0] $end
$var wire 32 = SRAA_in [31:0] $end
$scope module row_block_indicator $end
$var wire 1 * clear $end
$var wire 1 . clk $end
$var wire 1 # increment $end
$var reg 2 > count [1:0] $end
$upscope $end
$scope module row_indicator $end
$var wire 1 ) clear $end
$var wire 1 . clk $end
$var reg 5 ? count [4:0] $end
$upscope $end
$scope module select_sraa_input $end
$var wire 32 @ in1 [31:0] $end
$var wire 32 A in2 [31:0] $end
$var wire 32 B in3 [31:0] $end
$var wire 2 C sel [1:0] $end
$var reg 32 D out [31:0] $end
$upscope $end
$scope module sraa_1 $end
$var wire 1 ( clear $end
$var wire 1 . clk $end
$var wire 16 E in [15:0] $end
$var wire 1 / info_bit $end
$var wire 1 F load $end
$var wire 1 " load_reg $end
$var wire 1 ! load_shift_reg $end
$var wire 16 G out [15:0] $end
$var wire 16 H current_gi [15:0] $end
$var reg 16 I reg_in [15:0] $end
$var reg 16 J temp [15:0] $end
$var integer 32 K iterator [31:0] $end
$scope module current_gi_calculator $end
$var wire 1 . clk $end
$var wire 16 L in [15:0] $end
$var wire 1 ! load $end
$var reg 16 M out [15:0] $end
$upscope $end
$scope module generate_final_output $end
$var wire 1 ( clear $end
$var wire 1 . clk $end
$var wire 16 N in [15:0] $end
$var wire 1 " load $end
$var reg 16 O out [15:0] $end
$upscope $end
$upscope $end
$scope module sraa_2 $end
$var wire 1 ( clear $end
$var wire 1 . clk $end
$var wire 16 P in [15:0] $end
$var wire 1 / info_bit $end
$var wire 1 Q load $end
$var wire 1 " load_reg $end
$var wire 1 ! load_shift_reg $end
$var wire 16 R out [15:0] $end
$var wire 16 S current_gi [15:0] $end
$var reg 16 T reg_in [15:0] $end
$var reg 16 U temp [15:0] $end
$var integer 32 V iterator [31:0] $end
$scope module current_gi_calculator $end
$var wire 1 . clk $end
$var wire 16 W in [15:0] $end
$var wire 1 ! load $end
$var reg 16 X out [15:0] $end
$upscope $end
$scope module generate_final_output $end
$var wire 1 ( clear $end
$var wire 1 . clk $end
$var wire 16 Y in [15:0] $end
$var wire 1 " load $end
$var reg 16 Z out [15:0] $end
$upscope $end
$upscope $end
$upscope $end
$upscope $end
$enddefinitions $end
#0
$dumpvars
bx Z
bx Y
bx X
b0 W
bx V
bx U
bx T
bx S
bx R
zQ
b0 P
bx O
bx N
bx M
b0 L
bx K
bx J
bx I
bx H
bx G
zF
b0 E
b0 D
bx C
b11111111111111111111111111111111 B
b11110000001111111111111110000000 A
b11111110000000110000111111110000 @
bx ?
bx >
b0 =
bx <
bx ;
bx :
b11111111111111111111111111111111 9
b11110000001111111111111110000000 8
b11111110000000110000111111110000 7
bx 6
bx 5
bx 4
bx 3
bx 2
x1
b110000111111000101001101110110111 0
x/
0.
b11111111111111111111111111111111 -
b11110000001111111111111110000000 ,
b11111110000000110000111111110000 +
x*
x)
x(
bx '
bx &
x%
bx $
x#
x"
x!
$end
#2000
11
#4000
0%
0#
0(
0"
0!
0)
0*
b0 5
#5000
b0 6
1.
#7000
b111111110000 P
b111111110000 W
b1111111000000011 E
b1111111000000011 L
b10000 V
b10000 K
b11111110000000110000111111110000 =
b11111110000000110000111111110000 D
b0 R
b0 Z
b0 $
b0 :
b0 G
b0 O
b0 &
b0 3
b0 ;
b0 ?
b0 '
b0 4
b0 <
b0 >
b0 C
1!
1(
1)
1*
b1 5
#10000
0.
#12000
b100000 2
01
#15000
b0xxxxxxxx0000 T
b0xxxxxxxx0000 Y
b0xxxxxxxx0000 U
b10000 V
bx0000000xx I
bx0000000xx N
bx0000000xx J
b10000 K
b1 6
b111111110000 S
b111111110000 X
b1111111000000011 H
b1111111000000011 M
1.
#17000
1"
0!
0(
0)
0*
b10 5
#20000
0.
#22000
b1111111000000011 I
b1111111000000011 N
b1111111000000011 J
b10000 K
b111111110000 T
b111111110000 Y
b111111110000 U
b10000 V
b11111 2
1/
#25000
b100000001000 T
b100000001000 Y
b11111111000 U
b10000 V
b1111111100000001 J
b100000010 I
b100000010 N
b10000 K
b1111111100000001 H
b1111111100000001 M
b11111111000 S
b11111111000 X
b10 6
b1 &
b1 3
b1 ;
b1 ?
b111111110000 R
b111111110000 Z
b11111110000000110000111111110000 $
b11111110000000110000111111110000 :
b1111111000000011 G
b1111111000000011 O
1.
#30000
0.
#32000
b11110 2
#35000
b1111111010000010 I
b1111111010000010 N
b1111111110000000 J
b10000 K
b101111110100 T
b101111110100 Y
b1111111100 U
b10000 V
b1111111100 S
b1111111100 X
b1111111110000000 H
b1111111110000000 M
b10 &
b10 3
b10 ;
b10 ?
b100000010 G
b100000010 O
b1000000100000100000001000 $
b1000000100000100000001000 :
b100000001000 R
b100000001000 Z
1.
#40000
0.
#42000
b100000010 I
b100000010 N
b0 J
b10000 K
b100000001000 T
b100000001000 Y
b0 U
b10000 V
b11101 2
0/
#45000
b10000 K
b10000 V
b111111111000000 H
b111111111000000 M
b111111110 S
b111111110 X
b11 &
b11 3
b11 ;
b11 ?
1.
#50000
0.
#52000
b11100 2
#55000
b10000 V
b10000 K
b11111111 S
b11111111 X
b11111111100000 H
b11111111100000 M
b100 &
b100 3
b100 ;
b100 ?
1.
#60000
0.
#62000
b11011 2
#65000
b10000 K
b10000 V
b1111111110000 H
b1111111110000 M
b1000000001111111 S
b1000000001111111 X
b101 &
b101 3
b101 ;
b101 ?
1.
#70000
0.
#72000
b11010 2
#75000
b10000 V
b10000 K
b1100000000111111 S
b1100000000111111 X
b111111111000 H
b111111111000 M
b110 &
b110 3
b110 ;
b110 ?
1.
#80000
0.
#82000
b111011111010 I
b111011111010 N
b111111111000 J
b10000 K
b1100100000110111 T
b1100100000110111 Y
b1100000000111111 U
b10000 V
b11001 2
1/
#85000
b1110000000011111 U
b10100000101000 T
b10100000101000 Y
b10000 V
b100100000110 I
b100100000110 N
b11111111100 J
b10000 K
b11111111100 H
b11111111100 M
b1110000000011111 S
b1110000000011111 X
b111 &
b111 3
b111 ;
b111 ?
b1100100000110111 R
b1100100000110111 Z
b1110111110101100100000110111 $
b1110111110101100100000110111 :
b111011111010 G
b111011111010 O
1.
#90000
0.
#92000
b11000 2
#95000
b101011111000 I
b101011111000 N
b1111111110 J
b10000 K
b1111000000001111 U
b1101100000100111 T
b1101100000100111 Y
b10000 V
b1111000000001111 S
b1111000000001111 X
b1111111110 H
b1111111110 M
b1000 &
b1000 3
b1000 ;
b1000 ?
b100100000110 G
b100100000110 O
b1001000001100010100000101000 $
b1001000001100010100000101000 :
b10100000101000 R
b10100000101000 Z
1.
#100000
0.
#102000
b10111 2
#105000
b1111100000000111 U
b10000000100000 T
b10000000100000 Y
b10000 V
b101100000111 I
b101100000111 N
b111111111 J
b10000 K
b111111111 H
b111111111 M
b1111100000000111 S
b1111100000000111 X
b1001 &
b1001 3
b1001 ;
b1001 ?
b1101100000100111 R
b1101100000100111 Z
b1010111110001101100000100111 $
b1010111110001101100000100111 :
b101011111000 G
b101011111000 O
1.
#110000
0.
#112000
b10110 2
#115000
b1000000011111111 J
b1000101111111000 I
b1000101111111000 N
b10000 K
b1111110000000011 U
b1101110000100011 T
b1101110000100011 Y
b10000 V
b1111110000000011 S
b1111110000000011 X
b1000000011111111 H
b1000000011111111 M
b1010 &
b1010 3
b1010 ;
b1010 ?
b101100000111 G
b101100000111 O
b1011000001110010000000100000 $
b1011000001110010000000100000 :
b10000000100000 R
b10000000100000 Z
1.
#120000
0.
#122000
b10101 2
#125000
b1111111000000001 U
b10001000100010 T
b10001000100010 Y
b10000 V
b1100000001111111 J
b100101110000111 I
b100101110000111 N
b10000 K
b1100000001111111 H
b1100000001111111 M
b1111111000000001 S
b1111111000000001 X
b1011 &
b1011 3
b1011 ;
b1011 ?
b1101110000100011 R
b1101110000100011 Z
b10001011111110001101110000100011 $
b10001011111110001101110000100011 :
b1000101111111000 G
b1000101111111000 O
1.
#130000
0.
#132000
b10100 2
#135000
b1110000000111111 J
b1010101110111000 I
b1010101110111000 N
b10000 K
b1101110100100010 T
b1101110100100010 Y
b1111111100000000 U
b10000 V
b1111111100000000 S
b1111111100000000 X
b1110000000111111 H
b1110000000111111 M
b1100 &
b1100 3
b1100 ;
b1100 ?
b100101110000111 G
b100101110000111 O
b1001011100001110010001000100010 $
b1001011100001110010001000100010 :
b10001000100010 R
b10001000100010 Z
1.
#140000
0.
#142000
b100101110000111 I
b100101110000111 N
b0 J
b10000 K
b10001000100010 T
b10001000100010 Y
b0 U
b10000 V
b10011 2
0/
#145000
b10000 K
b10000 V
b1111000000011111 H
b1111000000011111 M
b111111110000000 S
b111111110000000 X
b1101 &
b1101 3
b1101 ;
b1101 ?
1.
#150000
0.
#152000
b10010 2
#155000
b10000 V
b10000 K
b11111111000000 S
b11111111000000 X
b1111100000001111 H
b1111100000001111 M
b1110 &
b1110 3
b1110 ;
b1110 ?
1.
#157000
1#
b11 5
#160000
0.
#162000
b10001 2
#165000
b1111111110000000 P
b1111111110000000 W
b1111000000111111 E
b1111000000111111 L
b10000 K
b10000 V
b11110000001111111111111110000000 =
b11110000001111111111111110000000 D
b1111110000000111 H
b1111110000000111 M
b1111111100000 S
b1111111100000 X
b11 6
b1 '
b1 4
b1 <
b1 >
b1 C
b1111 &
b1111 3
b1111 ;
b1111 ?
1.
#167000
b0 &
b0 3
b0 ;
b0 ?
1!
1)
0#
b100 5
#170000
0.
#172000
b1011011110000000 I
b1011011110000000 N
b1111110000000111 J
b10000 K
b11110111000010 T
b11110111000010 Y
b1111111100000 U
b10000 V
b10000 2
1/
#175000
b1111000000111111 J
b100011110111111 I
b100011110111111 N
b10000 K
b1100001001000010 T
b1100001001000010 Y
b1111111110000000 U
b10000 V
b100 6
b1111111110000000 S
b1111111110000000 X
b1111000000111111 H
b1111000000111111 M
b1011011110000000 G
b1011011110000000 O
b10110111100000000011110111000010 $
b10110111100000000011110111000010 :
b11110111000010 R
b11110111000010 Z
1.
#177000
0)
0!
b10 5
#180000
0.
#182000
b1011011110000000 I
b1011011110000000 N
b0 J
b10000 K
b11110111000010 T
b11110111000010 Y
b0 U
b10000 V
b1111 2
0/
#185000
b10000 K
b10000 V
b1111100000011111 H
b1111100000011111 M
b111111111000000 S
b111111111000000 X
b10 6
b1 &
b1 3
b1 ;
b1 ?
1.
#190000
0.
#192000
b100111110011111 I
b100111110011111 N
b1111100000011111 J
b10000 K
b100001000000010 T
b100001000000010 Y
b111111111000000 U
b10000 V
b1110 2
1/
#195000
b1111110000001111 J
b1011001110010000 I
b1011001110010000 N
b10000 K
b111110111100010 T
b111110111100010 Y
b11111111100000 U
b10000 V
b11111111100000 S
b11111111100000 X
b1111110000001111 H
b1111110000001111 M
b10 &
b10 3
b10 ;
b10 ?
b100111110011111 G
b100111110011111 O
b1001111100111110100001000000010 $
b1001111100111110100001000000010 :
b100001000000010 R
b100001000000010 Z
1.
#200000
0.
#202000
b100111110011111 I
b100111110011111 N
b0 J
b10000 K
b100001000000010 T
b100001000000010 Y
b0 U
b10000 V
b1101 2
0/
#205000
b10000 K
b10000 V
b1111111000000111 H
b1111111000000111 M
b1111111110000 S
b1111111110000 X
b11 &
b11 3
b11 ;
b11 ?
1.
#210000
0.
#212000
b1100 2
#215000
b10000 V
b10000 K
b111111111000 S
b111111111000 X
b1111111100000011 H
b1111111100000011 M
b100 &
b100 3
b100 ;
b100 ?
1.
#220000
0.
#222000
b1011000010011100 I
b1011000010011100 N
b1111111100000011 J
b10000 K
b100110111111010 T
b100110111111010 Y
b111111111000 U
b10000 V
b1011 2
1/
#225000
b100101000000110 T
b100101000000110 Y
b11111111100 U
b10000 V
b1111111110000001 J
b100111100011101 I
b100111100011101 N
b10000 K
b1111111110000001 H
b1111111110000001 M
b11111111100 S
b11111111100 X
b101 &
b101 3
b101 ;
b101 ?
b100110111111010 R
b100110111111010 Z
b10110000100111000100110111111010 $
b10110000100111000100110111111010 :
b1011000010011100 G
b1011000010011100 O
1.
#230000
0.
#232000
b1010 2
#235000
b1011000011011101 I
b1011000011011101 N
b1111111111000000 J
b10000 K
b100100111111000 T
b100100111111000 Y
b1111111110 U
b10000 V
b1111111110 S
b1111111110 X
b1111111111000000 H
b1111111111000000 M
b110 &
b110 3
b110 ;
b110 ?
b100111100011101 G
b100111100011101 O
b1001111000111010100101000000110 $
b1001111000111010100101000000110 :
b100101000000110 R
b100101000000110 Z
1.
#240000
0.
#242000
b100111100011101 I
b100111100011101 N
b0 J
b10000 K
b100101000000110 T
b100101000000110 Y
b0 U
b10000 V
b1001 2
0/
#245000
b10000 K
b10000 V
b111111111100000 H
b111111111100000 M
b111111111 S
b111111111 X
b111 &
b111 3
b111 ;
b111 ?
1.
#250000
0.
#252000
b11000011111101 I
b11000011111101 N
b111111111100000 J
b10000 K
b100101111111001 T
b100101111111001 Y
b111111111 U
b10000 V
b1000 2
1/
#255000
b111100001101 I
b111100001101 N
b11111111110000 J
b10000 K
b1000000011111111 U
b1100101100000110 T
b1100101100000110 Y
b10000 V
b1000000011111111 S
b1000000011111111 X
b11111111110000 H
b11111111110000 M
b1000 &
b1000 3
b1000 ;
b1000 ?
b11000011111101 G
b11000011111101 O
b110000111111010100101111111001 $
b110000111111010100101111111001 :
b100101111111001 R
b100101111111001 Z
1.
#260000
0.
#262000
b111 2
#265000
b1100000001111111 U
b101101111001 T
b101101111001 Y
b10000 V
b1000011110101 I
b1000011110101 N
b1111111111000 J
b10000 K
b1111111111000 H
b1111111111000 M
b1100000001111111 S
b1100000001111111 X
b1001 &
b1001 3
b1001 ;
b1001 ?
b1100101100000110 R
b1100101100000110 Z
b1111000011011100101100000110 $
b1111000011011100101100000110 :
b111100001101 G
b111100001101 O
1.
#270000
0.
#272000
b110 2
#275000
b1111100001001 I
b1111100001001 N
b111111111100 J
b10000 K
b1110000000111111 U
b1110101101000110 T
b1110101101000110 Y
b10000 V
b1110000000111111 S
b1110000000111111 X
b111111111100 H
b111111111100 M
b1010 &
b1010 3
b1010 ;
b1010 ?
b1000011110101 G
b1000011110101 O
b10000111101010000101101111001 $
b10000111101010000101101111001 :
b101101111001 R
b101101111001 Z
1.
#280000
0.
#282000
b1000011110101 I
b1000011110101 N
b0 J
b10000 K
b101101111001 T
b101101111001 Y
b0 U
b10000 V
b101 2
0/
#285000
b10000 K
b10000 V
b11111111110 H
b11111111110 M
b1111000000011111 S
b1111000000011111 X
b1011 &
b1011 3
b1011 ;
b1011 ?
1.
#290000
0.
#292000
b1011100001011 I
b1011100001011 N
b11111111110 J
b10000 K
b1111101101100110 T
b1111101101100110 Y
b1111000000011111 U
b10000 V
b100 2
1/
#295000
b1010011110100 I
b1010011110100 N
b1111111111 J
b10000 K
b1111100000001111 U
b1101101001 T
b1101101001 Y
b10000 V
b1111100000001111 S
b1111100000001111 X
b1111111111 H
b1111111111 M
b1100 &
b1100 3
b1100 ;
b1100 ?
b1011100001011 G
b1011100001011 O
b10111000010111111101101100110 $
b10111000010111111101101100110 :
b1111101101100110 R
b1111101101100110 Z
1.
#300000
0.
#302000
b11 2
#305000
b1111110000000111 U
b1111111101101110 T
b1111111101101110 Y
b10000 V
b1000000111111111 J
b1001010100001011 I
b1001010100001011 N
b10000 K
b1000000111111111 H
b1000000111111111 M
b1111110000000111 S
b1111110000000111 X
b1101 &
b1101 3
b1101 ;
b1101 ?
b1101101001 R
b1101101001 Z
b10100111101000000001101101001 $
b10100111101000000001101101001 :
b1010011110100 G
b1010011110100 O
1.
#310000
0.
#312000
b1010011110100 I
b1010011110100 N
b0 J
b10000 K
b1101101001 T
b1101101001 Y
b0 U
b10000 V
b10 2
0/
#315000
b10000 V
b10000 K
b1111111000000011 S
b1111111000000011 X
b1100000011111111 H
b1100000011111111 M
b1110 &
b1110 3
b1110 ;
b1110 ?
1.
#317000
1#
b11 5
#320000
0.
#322000
b1101010000001011 I
b1101010000001011 N
b1100000011111111 J
b10000 K
b1111110101101010 T
b1111110101101010 Y
b1111111000000011 U
b10000 V
b1 2
1/
#325000
b1111111111111111 P
b1111111111111111 W
b1111111111111111 E
b1111111111111111 L
b11111111111111111111111111111111 =
b11111111111111111111111111111111 D
b1111111100000001 U
b1001101011 T
b1001101011 Y
b10000 V
b1110000001111111 J
b11010001110100 I
b11010001110100 N
b10000 K
b1110000001111111 H
b1110000001111111 M
b1111111100000001 S
b1111111100000001 X
b11 6
b10 '
b10 4
b10 <
b10 >
b10 C
b1111 &
b1111 3
b1111 ;
b1111 ?
b1111110101101010 R
b1111110101101010 Z
b11010100000010111111110101101010 $
b11010100000010111111110101101010 :
b1101010000001011 G
b1101010000001011 O
1.
#327000
b0 &
b0 3
b0 ;
b0 ?
1!
1)
0#
b100 5
#330000
0.
#332000
b0 2
#335000
b1111111111111111 J
b1100101110001011 I
b1100101110001011 N
b10000 K
b1111111111111111 U
b1111110110010100 T
b1111110110010100 Y
b10000 V
b100 6
b1111111111111111 S
b1111111111111111 X
b1111111111111111 H
b1111111111111111 M
b11010001110100 G
b11010001110100 O
b110100011101000000001001101011 $
b110100011101000000001001101011 :
b1001101011 R
b1001101011 Z
1.
#337000
0)
0!
b10 5
#340000
0.
#342000
b11111111111111111111111111111111 2
#345000
b1001101011 T
b1001101011 Y
b10000 V
b11010001110100 I
b11010001110100 N
b10000 K
b10 6
b1 &
b1 3
b1 ;
b1 ?
b1111110110010100 R
b1111110110010100 Z
b11001011100010111111110110010100 $
b11001011100010111111110110010100 :
b1100101110001011 G
b1100101110001011 O
1.
#347000
0"
1%
b101 5
#350000
0.
#355000
b101 6
b10 &
b10 3
b10 ;
b10 ?
1.
#360000
0.
#365000
b11 &
b11 3
b11 ;
b11 ?
1.
#370000
0.
#375000
b100 &
b100 3
b100 ;
b100 ?
1.
#380000
0.
#385000
b101 &
b101 3
b101 ;
b101 ?
1.
#390000
0.
#395000
b110 &
b110 3
b110 ;
b110 ?
1.
#400000
0.
#405000
b111 &
b111 3
b111 ;
b111 ?
1.
#410000
0.
#415000
b1000 &
b1000 3
b1000 ;
b1000 ?
1.
#420000
0.
#425000
b1001 &
b1001 3
b1001 ;
b1001 ?
1.
#430000
0.
#435000
b1010 &
b1010 3
b1010 ;
b1010 ?
1.
